{
  "4639": {
    "averageSquareMeterPrice": 42881,
    "pricePercentageChangeLastYear": 2.3,
    "pricePercentageChangeLastQuarter": 2.8,
    "pricePercentageChangeLastMonth": null,
    "averageSalesTimeInDays": 33,
    "numberOfEstatesSoldLastQuarter": 842,
    "numberOfEstatesSoldLastMonth": null
  },
  "4617": {
    "averageSquareMeterPrice": 42881,
    "pricePercentageChangeLastYear": 2.3,
    "pricePercentageChangeLastQuarter": 2.8,
    "pricePercentageChangeLastMonth": null,
    "averageSalesTimeInDays": 33,
    "numberOfEstatesSoldLastQuarter": 842,
    "numberOfEstatesSoldLastMonth": null
  },
  "4614": {
    "averageSquareMeterPrice": 42881,
    "pricePercentageChangeLastYear": 2.3,
    "pricePercentageChangeLastQuarter": 2.8,
    "pricePercentageChangeLastMonth": null,
    "averageSalesTimeInDays": 33,
    "numberOfEstatesSoldLastQuarter": 842,
    "numberOfEstatesSoldLastMonth": null
  },
  "4634": {
    "averageSquareMeterPrice": 42881,
    "pricePercentageChangeLastYear": 2.3,
    "pricePercentageChangeLastQuarter": 2.8,
    "pricePercentageChangeLastMonth": null,
    "averageSalesTimeInDays": 33,
    "numberOfEstatesSoldLastQuarter": 842,
    "numberOfEstatesSoldLastMonth": null
  },
  "4624": {
    "averageSquareMeterPrice": 42881,
    "pricePercentageChangeLastYear": 2.3,
    "pricePercentageChangeLastQuarter": 2.8,
    "pricePercentageChangeLastMonth": null,
    "averageSalesTimeInDays": 33,
    "numberOfEstatesSoldLastQuarter": 842,
    "numberOfEstatesSoldLastMonth": null
  },
  "4616": {
    "averageSquareMeterPrice": 42881,
    "pricePercentageChangeLastYear": 2.3,
    "pricePercentageChangeLastQuarter": 2.8,
    "pricePercentageChangeLastMonth": null,
    "averageSalesTimeInDays": 33,
    "numberOfEstatesSoldLastQuarter": 842,
    "numberOfEstatesSoldLastMonth": null
  },
  "4637": {
    "averageSquareMeterPrice": 42881,
    "pricePercentageChangeLastYear": 2.3,
    "pricePercentageChangeLastQuarter": 2.8,
    "pricePercentageChangeLastMonth": null,
    "averageSalesTimeInDays": 33,
    "numberOfEstatesSoldLastQuarter": 842,
    "numberOfEstatesSoldLastMonth": null
  },
  "4632": {
    "averageSquareMeterPrice": 42881,
    "pricePercentageChangeLastYear": 2.3,
    "pricePercentageChangeLastQuarter": 2.8,
    "pricePercentageChangeLastMonth": null,
    "averageSalesTimeInDays": 33,
    "numberOfEstatesSoldLastQuarter": 842,
    "numberOfEstatesSoldLastMonth": null
  },
  "4611": {
    "averageSquareMeterPrice": 42881,
    "pricePercentageChangeLastYear": 2.3,
    "pricePercentageChangeLastQuarter": 2.8,
    "pricePercentageChangeLastMonth": null,
    "averageSalesTimeInDays": 33,
    "numberOfEstatesSoldLastQuarter": 842,
    "numberOfEstatesSoldLastMonth": null
  },
  "4612": {
    "averageSquareMeterPrice": 42881,
    "pricePercentageChangeLastYear": 2.3,
    "pricePercentageChangeLastQuarter": 2.8,
    "pricePercentageChangeLastMonth": null,
    "averageSalesTimeInDays": 33,
    "numberOfEstatesSoldLastQuarter": 842,
    "numberOfEstatesSoldLastMonth": null
  },
  "4608": {
    "averageSquareMeterPrice": 42881,
    "pricePercentageChangeLastYear": 2.3,
    "pricePercentageChangeLastQuarter": 2.8,
    "pricePercentageChangeLastMonth": null,
    "averageSalesTimeInDays": 33,
    "numberOfEstatesSoldLastQuarter": 842,
    "numberOfEstatesSoldLastMonth": null
  },
  "4610": {
    "averageSquareMeterPrice": 42881,
    "pricePercentageChangeLastYear": 2.3,
    "pricePercentageChangeLastQuarter": 2.8,
    "pricePercentageChangeLastMonth": null,
    "averageSalesTimeInDays": 33,
    "numberOfEstatesSoldLastQuarter": 842,
    "numberOfEstatesSoldLastMonth": null
  },
  "4613": {
    "averageSquareMeterPrice": 42881,
    "pricePercentageChangeLastYear": 2.3,
    "pricePercentageChangeLastQuarter": 2.8,
    "pricePercentageChangeLastMonth": null,
    "averageSalesTimeInDays": 33,
    "numberOfEstatesSoldLastQuarter": 842,
    "numberOfEstatesSoldLastMonth": null
  },
  "4615": {
    "averageSquareMeterPrice": 42881,
    "pricePercentageChangeLastYear": 2.3,
    "pricePercentageChangeLastQuarter": 2.8,
    "pricePercentageChangeLastMonth": null,
    "averageSalesTimeInDays": 33,
    "numberOfEstatesSoldLastQuarter": 842,
    "numberOfEstatesSoldLastMonth": null
  },
  "4620": {
    "averageSquareMeterPrice": 42881,
    "pricePercentageChangeLastYear": 2.3,
    "pricePercentageChangeLastQuarter": 2.8,
    "pricePercentageChangeLastMonth": null,
    "averageSalesTimeInDays": 33,
    "numberOfEstatesSoldLastQuarter": 842,
    "numberOfEstatesSoldLastMonth": null
  },
  "4621": {
    "averageSquareMeterPrice": 42881,
    "pricePercentageChangeLastYear": 2.3,
    "pricePercentageChangeLastQuarter": 2.8,
    "pricePercentageChangeLastMonth": null,
    "averageSalesTimeInDays": 33,
    "numberOfEstatesSoldLastQuarter": 842,
    "numberOfEstatesSoldLastMonth": null
  },
  "4622": {
    "averageSquareMeterPrice": 42881,
    "pricePercentageChangeLastYear": 2.3,
    "pricePercentageChangeLastQuarter": 2.8,
    "pricePercentageChangeLastMonth": null,
    "averageSalesTimeInDays": 33,
    "numberOfEstatesSoldLastQuarter": 842,
    "numberOfEstatesSoldLastMonth": null
  },
  "4623": {
    "averageSquareMeterPrice": 42881,
    "pricePercentageChangeLastYear": 2.3,
    "pricePercentageChangeLastQuarter": 2.8,
    "pricePercentageChangeLastMonth": null,
    "averageSalesTimeInDays": 33,
    "numberOfEstatesSoldLastQuarter": 842,
    "numberOfEstatesSoldLastMonth": null
  },
  "4626": {
    "averageSquareMeterPrice": 42881,
    "pricePercentageChangeLastYear": 2.3,
    "pricePercentageChangeLastQuarter": 2.8,
    "pricePercentageChangeLastMonth": null,
    "averageSalesTimeInDays": 33,
    "numberOfEstatesSoldLastQuarter": 842,
    "numberOfEstatesSoldLastMonth": null
  },
  "4628": {
    "averageSquareMeterPrice": 42881,
    "pricePercentageChangeLastYear": 2.3,
    "pricePercentageChangeLastQuarter": 2.8,
    "pricePercentageChangeLastMonth": null,
    "averageSalesTimeInDays": 33,
    "numberOfEstatesSoldLastQuarter": 842,
    "numberOfEstatesSoldLastMonth": null
  },
  "4629": {
    "averageSquareMeterPrice": 42881,
    "pricePercentageChangeLastYear": 2.3,
    "pricePercentageChangeLastQuarter": 2.8,
    "pricePercentageChangeLastMonth": null,
    "averageSalesTimeInDays": 33,
    "numberOfEstatesSoldLastQuarter": 842,
    "numberOfEstatesSoldLastMonth": null
  },
  "4631": {
    "averageSquareMeterPrice": 42881,
    "pricePercentageChangeLastYear": 2.3,
    "pricePercentageChangeLastQuarter": 2.8,
    "pricePercentageChangeLastMonth": null,
    "averageSalesTimeInDays": 33,
    "numberOfEstatesSoldLastQuarter": 842,
    "numberOfEstatesSoldLastMonth": null
  },
  "4633": {
    "averageSquareMeterPrice": 42881,
    "pricePercentageChangeLastYear": 2.3,
    "pricePercentageChangeLastQuarter": 2.8,
    "pricePercentageChangeLastMonth": null,
    "averageSalesTimeInDays": 33,
    "numberOfEstatesSoldLastQuarter": 842,
    "numberOfEstatesSoldLastMonth": null
  },
  "4638": {
    "averageSquareMeterPrice": 42881,
    "pricePercentageChangeLastYear": 2.3,
    "pricePercentageChangeLastQuarter": 2.8,
    "pricePercentageChangeLastMonth": null,
    "averageSalesTimeInDays": 33,
    "numberOfEstatesSoldLastQuarter": 842,
    "numberOfEstatesSoldLastMonth": null
  },
  "4630": {
    "averageSquareMeterPrice": 42881,
    "pricePercentageChangeLastYear": 2.3,
    "pricePercentageChangeLastQuarter": 2.8,
    "pricePercentageChangeLastMonth": null,
    "averageSalesTimeInDays": 33,
    "numberOfEstatesSoldLastQuarter": 842,
    "numberOfEstatesSoldLastMonth": null
  },
  "4618": {
    "averageSquareMeterPrice": 42881,
    "pricePercentageChangeLastYear": 2.3,
    "pricePercentageChangeLastQuarter": 2.8,
    "pricePercentageChangeLastMonth": null,
    "averageSalesTimeInDays": 33,
    "numberOfEstatesSoldLastQuarter": 842,
    "numberOfEstatesSoldLastMonth": null
  },
  "4635": {
    "averageSquareMeterPrice": 42881,
    "pricePercentageChangeLastYear": 2.3,
    "pricePercentageChangeLastQuarter": 2.8,
    "pricePercentageChangeLastMonth": null,
    "averageSalesTimeInDays": 33,
    "numberOfEstatesSoldLastQuarter": 842,
    "numberOfEstatesSoldLastMonth": null
  },
  "4636": {
    "averageSquareMeterPrice": 42881,
    "pricePercentageChangeLastYear": 2.3,
    "pricePercentageChangeLastQuarter": 2.8,
    "pricePercentageChangeLastMonth": null,
    "averageSalesTimeInDays": 33,
    "numberOfEstatesSoldLastQuarter": 842,
    "numberOfEstatesSoldLastMonth": null
  }
}
