{
    "trondheim": {
      "lat": 63.4274,
      "lng": 10.3942
    },
    "bergen": {
      "lat": 60.396756,
      "lng": 5.3249
    },
    "bodo": {
      "lat": 67.2879,
      "lng": 14.4398
    },
    "drammen": {
      "lat": 59.7420,
      "lng": 10.2029
    },
    "kristiansand": {
      "lat": 58.1576,
      "lng": 8.0165
    },
    "oslo": {
      "lat": 59.9240,
      "lng": 10.7589
    },
    "stavanger": {
      "lat": 58.9679,
      "lng": 5.7328
    },
    "tromso": {
      "lat": 69.6667,
      "lng": 18.9726
    }
  }